{"name":": Deve ser capaz de realizar operacoes de soma com dois numeros","id":"soma;:-deve-ser-capaz-de-realizar-operacoes-de-soma-com-dois-numeros","testSteps":[{"number":1,"description":"Example: {primeiro_numero\u003d5, segundo_numero\u003d8, resultado\u003d13}","duration":60,"startTime":"2021-02-07T20:49:32.764-03:00[America/Sao_Paulo]","exception":{"errorType":"net.thucydides.core.annotations.NotImplementedException","message":"","stackTrace":[{"declaringClass":"functional.stepdef.calculadora.soma.SomaStepDef","methodName":"que_o_usuario_deseja_realizar_uma_operacao_de_soma","fileName":"SomaStepDef.java","lineNumber":15},{"declaringClass":"✽","methodName":"que o usuario deseja realizar uma operacao de soma","fileName":"classpath:features/calculadora/soma_subtracao/soma.feature","lineNumber":8}]},"result":"ERROR","precondition":false,"level":0,"lineNumber":13,"children":[{"number":2,"description":"Dado que o usuario deseja realizar uma operacao de soma","duration":33,"startTime":"2021-02-07T20:49:32.772-03:00[America/Sao_Paulo]","exception":{"errorType":"net.thucydides.core.annotations.NotImplementedException","message":"","stackTrace":[{"declaringClass":"functional.stepdef.calculadora.soma.SomaStepDef","methodName":"que_o_usuario_deseja_realizar_uma_operacao_de_soma","fileName":"SomaStepDef.java","lineNumber":15},{"declaringClass":"✽","methodName":"que o usuario deseja realizar uma operacao de soma","fileName":"classpath:features/calculadora/soma_subtracao/soma.feature","lineNumber":8}]},"result":"ERROR","precondition":false,"level":1},{"number":3,"description":"Quando ele  tenta somar o 5 o 8","duration":2,"startTime":"2021-02-07T20:49:32.813-03:00[America/Sao_Paulo]","result":"SKIPPED","precondition":false,"level":1},{"number":4,"description":"Entao o sistema deve retornar 13","duration":1,"startTime":"2021-02-07T20:49:32.816-03:00[America/Sao_Paulo]","result":"SKIPPED","precondition":false,"level":1}]},{"number":5,"description":"Example: {primeiro_numero\u003d100, segundo_numero\u003d0, resultado\u003d0}","duration":17,"startTime":"2021-02-07T20:49:32.888-03:00[America/Sao_Paulo]","exception":{"errorType":"net.thucydides.core.annotations.NotImplementedException","message":"","stackTrace":[{"declaringClass":"functional.stepdef.calculadora.soma.SomaStepDef","methodName":"que_o_usuario_deseja_realizar_uma_operacao_de_soma","fileName":"SomaStepDef.java","lineNumber":15},{"declaringClass":"✽","methodName":"que o usuario deseja realizar uma operacao de soma","fileName":"classpath:features/calculadora/soma_subtracao/soma.feature","lineNumber":8}]},"result":"ERROR","precondition":false,"level":0,"lineNumber":14,"children":[{"number":6,"description":"Dado que o usuario deseja realizar uma operacao de soma","duration":6,"startTime":"2021-02-07T20:49:32.889-03:00[America/Sao_Paulo]","exception":{"errorType":"net.thucydides.core.annotations.NotImplementedException","message":"","stackTrace":[{"declaringClass":"functional.stepdef.calculadora.soma.SomaStepDef","methodName":"que_o_usuario_deseja_realizar_uma_operacao_de_soma","fileName":"SomaStepDef.java","lineNumber":15},{"declaringClass":"✽","methodName":"que o usuario deseja realizar uma operacao de soma","fileName":"classpath:features/calculadora/soma_subtracao/soma.feature","lineNumber":8}]},"result":"ERROR","precondition":false,"level":1},{"number":7,"description":"Quando ele  tenta somar o 100 o 0","duration":1,"startTime":"2021-02-07T20:49:32.897-03:00[America/Sao_Paulo]","result":"SKIPPED","precondition":false,"level":1},{"number":8,"description":"Entao o sistema deve retornar 0","duration":2,"startTime":"2021-02-07T20:49:32.899-03:00[America/Sao_Paulo]","result":"SKIPPED","precondition":false,"level":1}]},{"number":9,"description":"Example: {primeiro_numero\u003d-1, segundo_numero\u003d1, resultado\u003d0}","duration":15,"startTime":"2021-02-07T20:49:32.913-03:00[America/Sao_Paulo]","exception":{"errorType":"net.thucydides.core.annotations.NotImplementedException","message":"","stackTrace":[{"declaringClass":"functional.stepdef.calculadora.soma.SomaStepDef","methodName":"que_o_usuario_deseja_realizar_uma_operacao_de_soma","fileName":"SomaStepDef.java","lineNumber":15},{"declaringClass":"✽","methodName":"que o usuario deseja realizar uma operacao de soma","fileName":"classpath:features/calculadora/soma_subtracao/soma.feature","lineNumber":8}]},"result":"ERROR","precondition":false,"level":0,"lineNumber":15,"children":[{"number":10,"description":"Dado que o usuario deseja realizar uma operacao de soma","duration":5,"startTime":"2021-02-07T20:49:32.915-03:00[America/Sao_Paulo]","exception":{"errorType":"net.thucydides.core.annotations.NotImplementedException","message":"","stackTrace":[{"declaringClass":"functional.stepdef.calculadora.soma.SomaStepDef","methodName":"que_o_usuario_deseja_realizar_uma_operacao_de_soma","fileName":"SomaStepDef.java","lineNumber":15},{"declaringClass":"✽","methodName":"que o usuario deseja realizar uma operacao de soma","fileName":"classpath:features/calculadora/soma_subtracao/soma.feature","lineNumber":8}]},"result":"ERROR","precondition":false,"level":1},{"number":11,"description":"Quando ele  tenta somar o -1 o 1","duration":1,"startTime":"2021-02-07T20:49:32.921-03:00[America/Sao_Paulo]","result":"SKIPPED","precondition":false,"level":1},{"number":12,"description":"Entao o sistema deve retornar 0","duration":1,"startTime":"2021-02-07T20:49:32.923-03:00[America/Sao_Paulo]","result":"SKIPPED","precondition":false,"level":1}]},{"number":13,"description":"Example: {primeiro_numero\u003d22.5, segundo_numero\u003d0.25, resultado\u003d22.75}","duration":16,"startTime":"2021-02-07T20:49:32.933-03:00[America/Sao_Paulo]","exception":{"errorType":"net.thucydides.core.annotations.NotImplementedException","message":"","stackTrace":[{"declaringClass":"functional.stepdef.calculadora.soma.SomaStepDef","methodName":"que_o_usuario_deseja_realizar_uma_operacao_de_soma","fileName":"SomaStepDef.java","lineNumber":15},{"declaringClass":"✽","methodName":"que o usuario deseja realizar uma operacao de soma","fileName":"classpath:features/calculadora/soma_subtracao/soma.feature","lineNumber":8}]},"result":"ERROR","precondition":false,"level":0,"lineNumber":16,"children":[{"number":14,"description":"Dado que o usuario deseja realizar uma operacao de soma","duration":6,"startTime":"2021-02-07T20:49:32.934-03:00[America/Sao_Paulo]","exception":{"errorType":"net.thucydides.core.annotations.NotImplementedException","message":"","stackTrace":[{"declaringClass":"functional.stepdef.calculadora.soma.SomaStepDef","methodName":"que_o_usuario_deseja_realizar_uma_operacao_de_soma","fileName":"SomaStepDef.java","lineNumber":15},{"declaringClass":"✽","methodName":"que o usuario deseja realizar uma operacao de soma","fileName":"classpath:features/calculadora/soma_subtracao/soma.feature","lineNumber":8}]},"result":"ERROR","precondition":false,"level":1},{"number":15,"description":"Quando ele  tenta somar o 22.5 o 0.25","duration":1,"startTime":"2021-02-07T20:49:32.941-03:00[America/Sao_Paulo]","result":"SKIPPED","precondition":false,"level":1},{"number":16,"description":"Entao o sistema deve retornar 22.75","duration":2,"startTime":"2021-02-07T20:49:32.943-03:00[America/Sao_Paulo]","result":"SKIPPED","precondition":false,"level":1}]}],"userStory":{"id":"soma","storyName":"Soma","path":"classpath:features/calculadora/soma_subtracao/soma.feature","narrative":"  Eu como usuário, desejo utilizar as operações de soma para realizar o calculo do dia a dia","type":"feature"},"featureTag":{"name":"Soma subtracao/Soma","type":"feature","displayName":"Soma subtracao/Soma"},"title":": Deve ser capaz de realizar operacoes de soma com dois numeros","description":"","tags":[{"name":"Calculadora/Soma subtracao","type":"capability","displayName":"Soma subtracao"},{"name":"Soma subtracao/Soma","type":"feature","displayName":"Soma"},{"name":"Calculadora","type":"theme","displayName":"Calculadora"}],"startTime":"2021-02-07T20:49:32.657-03:00[America/Sao_Paulo]","duration":293,"testFailureCause":{"errorType":"net.thucydides.core.annotations.NotImplementedException","message":"","stackTrace":[{"declaringClass":"functional.stepdef.calculadora.soma.SomaStepDef","methodName":"que_o_usuario_deseja_realizar_uma_operacao_de_soma","fileName":"SomaStepDef.java","lineNumber":15},{"declaringClass":"✽","methodName":"que o usuario deseja realizar uma operacao de soma","fileName":"classpath:features/calculadora/soma_subtracao/soma.feature","lineNumber":8}]},"testFailureClassname":"net.thucydides.core.annotations.NotImplementedException","testFailureMessage":"","testFailureSummary":"ERROR;net.thucydides.core.annotations.NotImplementedException;;SomaStepDef.java","projectKey":"","isManualTestingUpToDate":false,"dataTable":{"headers":["primeiro_numero","segundo_numero","resultado"],"rows":[{"values":["5","8","13"],"lineNumber":13,"result":"ERROR"},{"values":["100","0","0"],"lineNumber":14,"result":"ERROR"},{"values":["-1","1","0"],"lineNumber":15,"result":"ERROR"},{"values":["22.5","0.25","22.75"],"lineNumber":16,"result":"ERROR"}],"predefinedRows":true,"scenarioOutline":"Dado que o usuario deseja realizar uma operacao de soma\n\rQuando ele  tenta somar o \u003cprimeiro_numero\u003e o \u003csegundo_numero\u003e\n\rEntao o sistema deve retornar \u003cresultado\u003e\n\r","dataSetDescriptors":[{"startRow":0,"rowCount":0,"name":"","description":""}]},"manual":false,"testSource":"Cucumber","result":"ERROR","scenarioOutline":"Dado que o usuario deseja realizar uma operacao de soma\nQuando ele  tenta somar o \u003cprimeiro_numero\u003e o \u003csegundo_numero\u003e\nEntao o sistema deve retornar \u003cresultado\u003e"}